networkconfigparser/__init__.py
networkconfigparser/documentline.py
networkconfigparser/parser.py
networkconfigparser/search_helpers.py
networkconfigparser-0.3.dist-info/licenses/LICENSE
networkconfigparser-0.3.dist-info/METADATA
networkconfigparser-0.3.dist-info/WHEEL
networkconfigparser-0.3.dist-info/top_level.txt
networkconfigparser-0.3.dist-info/RECORD
