Metadata-Version: 2.4
Name: NetworkConfigParser
Version: 0.3
Summary: Parser and searching tools for network device configurations, such as Cisco IOS and Juniper JunOS
Author-email: Brian T Knight <code@knight-networks.com>
License-Expression: GPL-3.0-or-later
Project-URL: Homepage, https://github.com/btknight/NetworkConfigParser
Project-URL: Issues, https://github.com/btknight/NetworkConfigParser/issues
Keywords: nos,network,ios,junos,config,configuration,cisco,juniper,regex,search,parse
Classifier: Programming Language :: Python :: 3
Classifier: Operating System :: OS Independent
Requires-Python: >=3.10
License-File: LICENSE
Dynamic: license-file
